naive/__init__.py
naive-0.0.3.dist-info/DESCRIPTION.rst
naive-0.0.3.dist-info/entry_points.txt
naive-0.0.3.dist-info/METADATA
naive-0.0.3.dist-info/metadata.json
naive-0.0.3.dist-info/RECORD
naive-0.0.3.dist-info/top_level.txt
naive-0.0.3.dist-info/WHEEL
