Metadata-Version: 2.0
Name: naive
Version: 0.0.3
Summary: A naive static site generator
Home-page: https://github.com/ahnjungho/naive
Author: Ahn Jungho
Author-email: ahnjungho@ahnjungho.org
License: MIT
Keywords: static site generator
Platform: UNKNOWN
Classifier: Development Status :: 3 - Alpha
Classifier: Intended Audience :: Developers
Classifier: License :: OSI Approved :: MIT License
Classifier: Programming Language :: Python :: 3
Classifier: Programming Language :: Python :: 3.4
Requires-Dist: Markdown
Requires-Dist: Jinja2
Requires-Dist: libsass
Requires-Dist: PyYAML
